raritan/__init__.py
raritan/rpc/Agent.py
raritan/rpc/Enumeration.py
raritan/rpc/Interface.py
raritan/rpc/Structure.py
raritan/rpc/Time.py
raritan/rpc/TypeInfo.py
raritan/rpc/Utils.py
raritan/rpc/ValueObject.py
raritan/rpc/__init__.py
raritan/rpc/typecheck.py
raritan/rpc/assetmgrmodel/__init__.py
raritan/rpc/auth/__init__.py
raritan/rpc/auth/ldapsrv/__init__.py
raritan/rpc/bulkcfg/__init__.py
raritan/rpc/bulkrpc/__init__.py
raritan/rpc/cascading/__init__.py
raritan/rpc/cert/__init__.py
raritan/rpc/cew/__init__.py
raritan/rpc/cfg/__init__.py
raritan/rpc/datetime/__init__.py
raritan/rpc/devsettings/__init__.py
raritan/rpc/diag/__init__.py
raritan/rpc/emdmodel/__init__.py
raritan/rpc/event/__init__.py
raritan/rpc/firmware/__init__.py
raritan/rpc/fitness/__init__.py
raritan/rpc/hmi/__init__.py
raritan/rpc/idl/__init__.py
raritan/rpc/jsonrpc/__init__.py
raritan/rpc/lhx/__init__.py
raritan/rpc/lhxmodel/__init__.py
raritan/rpc/logging/__init__.py
raritan/rpc/modbus/__init__.py
raritan/rpc/modelpush/__init__.py
raritan/rpc/net/__init__.py
raritan/rpc/opaque/__init__.py
raritan/rpc/opaque/bulkrpc.py
raritan/rpc/pdumodel/__init__.py
raritan/rpc/peripheral/__init__.py
raritan/rpc/portsmodel/__init__.py
raritan/rpc/powerlogic/__init__.py
raritan/rpc/production/__init__.py
raritan/rpc/radius/__init__.py
raritan/rpc/res_mon/__init__.py
raritan/rpc/security/__init__.py
raritan/rpc/sensors/__init__.py
raritan/rpc/serial/__init__.py
raritan/rpc/servermon/__init__.py
raritan/rpc/session/__init__.py
raritan/rpc/smartcard/__init__.py
raritan/rpc/sys/__init__.py
raritan/rpc/test/__init__.py
raritan/rpc/tfw/__init__.py
raritan/rpc/um/__init__.py
raritan/rpc/usb/__init__.py
raritan/rpc/usermgmt/__init__.py
raritan/rpc/webcam/__init__.py
raritan-20210223.0.dist-info/LICENSE.md
raritan-20210223.0.dist-info/METADATA
raritan-20210223.0.dist-info/WHEEL
raritan-20210223.0.dist-info/top_level.txt
raritan-20210223.0.dist-info/RECORD
